profiplots/__init__.py
profiplots/_patch.py
profiplots/color.py
profiplots/profile.py
profiplots/settings.py
profiplots/style/__init__.py
profiplots/style/_modifier.py
profiplots/style/_utils.py
profiplots/theme/__init__.py
profiplots/theme/_plotnine.py
profiplots/theme/default.mplstyle
profiplots-3.0.5.dist-info/METADATA
profiplots-3.0.5.dist-info/WHEEL
profiplots-3.0.5.dist-info/top_level.txt
profiplots-3.0.5.dist-info/RECORD
